LICENSE
MANIFEST.in
README.md
setup.cfg
setup.py
django_rest_elasticsearch.egg-info/PKG-INFO
django_rest_elasticsearch.egg-info/SOURCES.txt
django_rest_elasticsearch.egg-info/dependency_links.txt
django_rest_elasticsearch.egg-info/requires.txt
django_rest_elasticsearch.egg-info/top_level.txt
rest_framework_elasticsearch/__init__.py
rest_framework_elasticsearch/es_filters.py
rest_framework_elasticsearch/es_inspector.py
rest_framework_elasticsearch/es_mixins.py
rest_framework_elasticsearch/es_pagination.py
rest_framework_elasticsearch/es_serializer.py
rest_framework_elasticsearch/es_validators.py
rest_framework_elasticsearch/es_views.py
tests/__init__.py
tests/conftest.py
tests/test_data.py
tests/test_filters.py
tests/test_mixins.py
tests/test_pagination.py
tests/test_serializers.py
tests/test_validators.py
tests/test_views.py
tests/utils.py